anomaly_ensemble_app/__init__.py
anomaly_ensemble_app/anomaly_data_preprocessing.py
anomaly_ensemble_app/anomaly_detection.py
anomaly_ensemble_app/anomaly_libs.py
anomaly_ensemble_app/anomaly_main.py
anomaly_ensemble_app/anomaly_models.py
anomaly_ensemble_app-0.0.4.dist-info/LICENSE
anomaly_ensemble_app-0.0.4.dist-info/METADATA
anomaly_ensemble_app-0.0.4.dist-info/WHEEL
anomaly_ensemble_app-0.0.4.dist-info/top_level.txt
anomaly_ensemble_app-0.0.4.dist-info/RECORD
